Workbook

Sheet Instruções
A1: INSTRUÇÕES
A2: 1 | B2: Atenção, só preencha as células em cinza nas abas seguintes!
A3: 2 | B3: Na aba "Definição de Parâmetros", defina os valores médios de salários para os cargos ali descritos bem como os investimentos diretos em divulgação, kit de boas vindas e outros. A partir daí, os demais cálculos serão feitos automaticamente.
A4: 3 | B4: Na aba "Custo Detalhado por Vaga", você encontra a descrição de todos os custos envolvidos no processo de contratação e as devidas explicações das premissas utilizadas. Além disso, consegue simular quanto a sua empresa gasta por ano em recrutamento e seleção estimando o número de contratações feitas no ano.

Sheet Definição de Parâmetros
A1: Profissionais envolvidos no Processo de R&S | B1: Salário Médio | C1: Salário Médio Aproximado com Encargos, Férias, 13º Salário | D1: Valor da Hora Trabalhada Aproximada com Encargos, Férias, 13º Salário
A2: Gestor da Vaga | B2: 1400 | C2: =1.7*B2 -> 2380 | D2: =C2/220 -> 10.818182
A3: Recrutador | B3: 1400 | C3: =1.7*B3 -> 2380 | D3: =C3/220 -> 10.818182
A4: Demais Colaboradores | B4: 1400 | C4: =1.7*B4 -> 2380 | D4: =C4/220 -> 10.818182
A5: Designer | B5: 1400 | C5: =1.7*B5 -> 2380 | D5: =C5/220 -> 10.818182
A7: Investimentos Diretos
A8: Verba para Kit de Boas Vindas ao Contratado | B8: 50
A9: Verba para Divulgação da cada Vaga | B9: 10
A10: Outros Investimentos | B10: 40

Sheet Custo Detalhado por Vaga
A1: Etapas do Recrutamento e Seleção | B1: Ações Específicas das Etapas | C1: Custos Envolvidos | D1: Descrição de Custos
A2: Planejamento da Vaga | B2: Briefing Gestor da Vaga + Responsável pelo Recrutamento | C2: =0.5*'Definição de Parâmetros'!D2+0.5*'Definição de Parâmetros'!D3 -> 10.818182 | D2: Reunião de 30 minutos entre gestor da vaga e recrutador para alinhamento de requisitos técnicos, comportamentais, dentre outros aspectos relevantes para a vaga.
B3: Cadastro da vaga e preenchimento de demais informações necessárias para divulgação | C3: =1.5*'Definição de Parâmetros'!D3 -> 16.227273 | D3: 1,5h do profissional de RH para preencher plataforma ou outro meio de controle e divulgação da vaga com todas as informações necessárias.
B4: Hora do profissional responsável pelo criativo (Arte, Vídeo, etc) para divulgação da vaga | C4: =1*'Definição de Parâmetros'!D5 -> 10.818182 | D4: Hora gasta para construir criativo da vaga.
B5: Custos Diretos de Divulgação (Anúncios) | C5: ='Definição de Parâmetros'!B10 -> 40 | D5: Valor destinado para divulgação da vaga
A6: Etapas do Processo de Seleção | B6: Triagem de Currículos | C6: =300*(3/60)*'Definição de Parâmetros'!D3 -> 162.27273 | D6: 3 minutos gastos para cada um dos 300 currículos analisados.
B7: Dinâmica | C7: =3*'Definição de Parâmetros'!D3*2+1.5*'Definição de Parâmetros'!D3 -> 81.136364 | D7: 3h duração dinâmica (2 profissionais) + 1,5h Preparação Dinâmica (1 profissional)
B8: Desafio | C8: =0.25*10*'Definição de Parâmetros'!D2 -> 27.045455 | D8: 15min para correção/análise de cada um dos desafios dos 10 candidatos pelo gestor
B9: Entrevista com Gestor | C9: =0.75*5*'Definição de Parâmetros'!D2+0.75*5*'Definição de Parâmetros'!D3 -> 81.136364 | D9: 45min por candidato por gestor e recrutador
B10: Entrevista de Fit Cultural | C10: =3*3*1*'Definição de Parâmetros'!D4 -> 97.363636 | D10: 1h de duração de cada entrevista com pelo menos 3 colaboradores da empresa
B11: Proposta Salarial | C11: =1*'Definição de Parâmetros'!D3 -> 10.818182 | D11: 1h do recrutador para negociação
B12: Demais orientações e direcionamentos ao candidato contratado | C12: =1.5*'Definição de Parâmetros'!D3 -> 16.227273 | D12: 1,5h do recrutador para demais orientações ao candidato contratado
A13: Outros Gastos | B13: Kit de Boas Vindas | C13: ='Definição de Parâmetros'!B8 -> 50 | D13: Valor destinado para Kit de Boas Vindas de cada colaborador
B14: Outros Investimentos
A15: TOTAL POR VAGA | C15: =SUM(C2:C14) -> 603.86364
A19: ESTIMAR GASTO TOTAL ANUAL?
A22: Preencha o Número Aproximado de Vagas Preenchidas por ano na sua Empresa | F22: 20
A23: TOTAL ANUAL | E23: =F22*C15 -> 12077.273
